collinearity_tool/__init__.py
collinearity_tool/collinearity_tool.py
collinearity_tool-0.1.7.dist-info/LICENSE
collinearity_tool-0.1.7.dist-info/WHEEL
collinearity_tool-0.1.7.dist-info/METADATA
collinearity_tool-0.1.7.dist-info/RECORD
