Metadata-Version: 2.1
Name: collinearity-tool
Version: 0.1.7
Summary: Identify multicollinearity issues by correlation, VIF, and visualizations.
Home-page: https://github.com/UBC-MDS/collinearity_tool
License: MIT
Author: Anahita Einolghozati, Chaoran Wang, Katia Aristova, Lisheng Mao
Requires-Python: >=3.9,<4.0
Classifier: License :: OSI Approved :: MIT License
Classifier: Programming Language :: Python :: 3
Classifier: Programming Language :: Python :: 3.10
Classifier: Programming Language :: Python :: 3.9
Requires-Dist: altair (>=4.2.0,<5.0.0)
Requires-Dist: numpy (>=1.22.1,<2.0.0)
Requires-Dist: pandas (>=1.3.5,<2.0.0)
Requires-Dist: patsy (>=0.5.2,<0.6.0)
Requires-Dist: statsmodels (>=0.13.1,<0.14.0)
Project-URL: Documentation, https://collinearity_tool.readthedocs.io
Project-URL: Repository, https://github.com/UBC-MDS/collinearity_tool
